quetz/__init__.py
quetz-0.0.0.dist-info/LICENSE
quetz-0.0.0.dist-info/METADATA
quetz-0.0.0.dist-info/WHEEL
quetz-0.0.0.dist-info/top_level.txt
quetz-0.0.0.dist-info/RECORD
