Metadata-Version: 2.1
Name: quetz
Version: 0.0.0
Summary: A Python library for compositional programming.
Home-page: https://github.com/hashberg-io/quetz
Author: hashberg
Author-email: sg495@users.noreply.github.com
License: UNKNOWN
Platform: UNKNOWN
Classifier: Programming Language :: Python :: 3.7
Classifier: Operating System :: OS Independent
Classifier: Development Status :: 1 - Planning
Classifier: Natural Language :: English
Classifier: Typing :: Typed
